iqm/applications/__init__.py
iqm/applications/applications.py
iqm/applications/graph_utils.py
iqm/applications/maxcut.py
iqm/applications/mis.py
iqm/applications/py.typed
iqm/applications/qubo.py
iqm/applications/sk.py
iqm/qaoa/__init__.py
iqm/qaoa/backends.py
iqm/qaoa/circuits.py
iqm/qaoa/generic_qaoa.py
iqm/qaoa/py.typed
iqm/qaoa/qubo_qaoa.py
iqm/qaoa/transforming_functions.py
iqm/qaoa/tree_qaoa.py
iqm/qaoa/transpiler/__init__.py
iqm/qaoa/transpiler/quantum_hardware.py
iqm/qaoa/transpiler/routing.py
iqm/qaoa/transpiler/rx_to_nx.py
iqm/qaoa/transpiler/hardwired/__init__.py
iqm/qaoa/transpiler/hardwired/hardwired.py
iqm/qaoa/transpiler/sn/__init__.py
iqm/qaoa/transpiler/sn/sn.py
iqm/qaoa/transpiler/sparse/__init__.py
iqm/qaoa/transpiler/sparse/edge_coloring.py
iqm/qaoa/transpiler/sparse/greedy_router.py
iqm/qaoa/transpiler/sparse/two_color_mapper.py
iqm/qaoa/transpiler/star/__init__.py
iqm/qaoa/transpiler/star/star.py
iqm/qaoa/tree_data_linear/angles.py
iqm_qaoa-1.35.0.dist-info/AUTHORS.rst
iqm_qaoa-1.35.0.dist-info/LICENSE.txt
iqm_qaoa-1.35.0.dist-info/METADATA
iqm_qaoa-1.35.0.dist-info/WHEEL
iqm_qaoa-1.35.0.dist-info/top_level.txt
iqm_qaoa-1.35.0.dist-info/RECORD
