Metadata-Version: 2.1
Name: iqm-qaoa
Version: 1.35.0
Summary: Set up and run QAOA experiments
Author-email: IQM Finland Oy <developers@meetiqm.com>
License: Copyright (c) 2024-2025 IQM Quantum Computers
Project-URL: Documentation, https://docs.meetiqm.com/iqm-qaoa/
Project-URL: Homepage, https://pypi.org/project/iqm-qaoa/
Classifier: Programming Language :: Python :: 3
Classifier: Topic :: Scientific/Engineering :: Physics
Classifier: Intended Audience :: Science/Research
Requires-Python: >=3.11
License-File: LICENSE.txt
License-File: AUTHORS.rst
Requires-Dist: iqm-client[qiskit] <33,>=32
Requires-Dist: iqm-client <33,>=32
Requires-Dist: iqm-station-control-client <12,>=11
Requires-Dist: iqm-exa-common <28,>=27
Requires-Dist: iqm-pulse <13,>=12
Requires-Dist: cvxpy >=1.5.3
Requires-Dist: dimod >=0.12.17
Requires-Dist: matplotlib >=3.9.0
Requires-Dist: networkx >=3.3
Requires-Dist: types-networkx
Requires-Dist: numpy >=1.24.0
Requires-Dist: qiskit >=1.2.4
Requires-Dist: qiskit-aer >=0.14.2
Requires-Dist: quimb >=1.8.4
Requires-Dist: requests >=2.32.3
Requires-Dist: scipy >=1.11.4
Requires-Dist: scipy-stubs
Requires-Dist: llvmlite >=0.44.0
Requires-Dist: numba >=0.61.0
Provides-Extra: notebook
Requires-Dist: iqm-client[qiskit] <33,>=32 ; extra == 'notebook'
Requires-Dist: iqm-client <33,>=32 ; extra == 'notebook'
Requires-Dist: iqm-station-control-client <12,>=11 ; extra == 'notebook'
Requires-Dist: iqm-exa-common <28,>=27 ; extra == 'notebook'
Requires-Dist: iqm-pulse <13,>=12 ; extra == 'notebook'
Requires-Dist: nbclient ~=0.5.10 ; extra == 'notebook'
Requires-Dist: notebook >=6.5.2 ; extra == 'notebook'
